LICENSE
README.md
README_ru.md
requirements.txt
setup.py
sevicfg.py
sevimon.py
sevistat.py
lib/cam.py
lib/centerface.py
lib/config.py
lib/guicfg.py
lib/i18n.py
lib/locale/__init__.py
lib/locale/ru.py
sevimon.egg-info/PKG-INFO
sevimon.egg-info/SOURCES.txt
sevimon.egg-info/dependency_links.txt
sevimon.egg-info/entry_points.txt
sevimon.egg-info/requires.txt
sevimon.egg-info/top_level.txt